{
	"file_path": "D:\\Что-то бесполезное\\modding\\addons\\games\\com.mojang\\development_behavior_packs\\arktludumthn_beh\\entities\\root.json",
	"file_type": "entity",
	"format_version": 1,
	"file_uuid": "7a9b3c39_84e0_472f_8545_929816b02c07",
	"file_version": 2,
	"cache_content": {
		"children": [
			{
				"data": "1.16.0",
				"key": "format_version"
			},
			{
				"open": {
					"format_version": "1.16.0",
					"minecraft:entity": {
						"description": {
							"identifier": "ark:root",
							"is_summonable": true,
							"is_spawnable": false,
							"is_experimental": false
						},
						"component_groups": {},
						"components": {
							"minecraft:movement": {
								"value": 0
							},
							"minecraft:movement.basic": {
								"max_turn": 30
							},
							"minecraft:attack": {
								"damage": 3
							},
							"minecraft:area_attack": {
								"damage_range": 0.2,
								"damage_per_tick": 1,
								"cause": "contact"
							},
							"minecraft:type_family": {
								"family": [
									"mob",
									"plant"
								]
							},
							"minecraft:collision_box": {
								"width": 1,
								"height": 2.5
							},
							"minecraft:health": {
								"max": 40,
								"value": 40
							},
							"minecraft:pushable": {
								"is_pushable": false,
								"is_pushable_by_piston": false
							},
							"minecraft:physics": {},
							"minecraft:behavior.look_at_target": {
								"priority": 0
							},
							"minecraft:behavior.nearest_attackable_target": {
								"priority": 1,
								"must_see": true,
								"within_radius": 10,
								"entity_types": [
									{
										"filters": {
											"any_of": [
												{
													"test": "is_family",
													"subject": "player"
												}
											]
										}
									}
								]
							},
							"minecraft:behavior.hurt_by_target": {
								"priority": 0
							}
						},
						"events": {}
					}
				},
				"key": "minecraft:entity",
				"children": [
					{
						"key": "description",
						"is_minified": true,
						"children": {
							"identifier": "ark:root",
							"is_summonable": true,
							"is_spawnable": false,
							"is_experimental": false
						}
					},
					{
						"key": "component_groups",
						"is_minified": true,
						"children": {}
					},
					{
						"open": {
							"description": {
								"identifier": "ark:root",
								"is_summonable": true,
								"is_spawnable": false,
								"is_experimental": false
							},
							"component_groups": {},
							"components": {
								"minecraft:movement": {
									"value": 0
								},
								"minecraft:movement.basic": {
									"max_turn": 30
								},
								"minecraft:attack": {
									"damage": 3
								},
								"minecraft:area_attack": {
									"damage_range": 0.2,
									"damage_per_tick": 1,
									"cause": "contact"
								},
								"minecraft:type_family": {
									"family": [
										"mob",
										"plant"
									]
								},
								"minecraft:collision_box": {
									"width": 1,
									"height": 2.5
								},
								"minecraft:health": {
									"max": 40,
									"value": 40
								},
								"minecraft:pushable": {
									"is_pushable": false,
									"is_pushable_by_piston": false
								},
								"minecraft:physics": {},
								"minecraft:behavior.look_at_target": {
									"priority": 0
								},
								"minecraft:behavior.nearest_attackable_target": {
									"priority": 1,
									"must_see": true,
									"within_radius": 10,
									"entity_types": [
										{
											"filters": {
												"any_of": [
													{
														"test": "is_family",
														"subject": "player"
													}
												]
											}
										}
									]
								},
								"minecraft:behavior.hurt_by_target": {
									"priority": 0
								}
							},
							"events": {}
						},
						"key": "components",
						"children": [
							{
								"key": "minecraft:movement",
								"is_minified": true,
								"children": {
									"value": 0
								}
							},
							{
								"key": "minecraft:movement.basic",
								"is_minified": true,
								"children": {
									"max_turn": 30
								}
							},
							{
								"key": "minecraft:attack",
								"is_minified": true,
								"children": {
									"damage": 3
								}
							},
							{
								"key": "minecraft:area_attack",
								"is_minified": true,
								"children": {
									"damage_range": 0.2,
									"damage_per_tick": 1,
									"cause": "contact"
								}
							},
							{
								"key": "minecraft:type_family",
								"is_minified": true,
								"children": {
									"family": [
										"mob",
										"plant"
									]
								}
							},
							{
								"key": "minecraft:collision_box",
								"is_minified": true,
								"children": {
									"width": 1,
									"height": 2.5
								}
							},
							{
								"key": "minecraft:health",
								"is_minified": true,
								"children": {
									"max": 40,
									"value": 40
								}
							},
							{
								"key": "minecraft:pushable",
								"is_minified": true,
								"children": {
									"is_pushable": false,
									"is_pushable_by_piston": false
								}
							},
							{
								"key": "minecraft:physics",
								"is_minified": true,
								"children": {}
							},
							{
								"key": "minecraft:behavior.look_at_target",
								"is_minified": true,
								"children": {
									"priority": 0
								}
							},
							{
								"key": "minecraft:behavior.nearest_attackable_target",
								"children": [
									{
										"data": "1",
										"key": "priority"
									},
									{
										"data": "true",
										"key": "must_see"
									},
									{
										"data": "10",
										"key": "within_radius"
									},
									{
										"open": {
											"priority": 1,
											"must_see": true,
											"within_radius": 10,
											"entity_types": [
												{
													"filters": {
														"any_of": [
															{
																"test": "is_family",
																"subject": "player"
															}
														]
													}
												}
											]
										},
										"key": "entity_types",
										"children": [
											{
												"open": [
													{
														"filters": {
															"any_of": [
																{
																	"test": "is_family",
																	"subject": "player"
																}
															]
														}
													}
												],
												"children": [
													{
														"open": {
															"filters": {
																"any_of": [
																	{
																		"test": "is_family",
																		"subject": "player"
																	}
																]
															}
														},
														"key": "filters",
														"children": [
															{
																"open": {
																	"any_of": [
																		{
																			"test": "is_family",
																			"subject": "player"
																		}
																	]
																},
																"key": "any_of",
																"children": [
																	{
																		"open": [
																			{
																				"test": "is_family",
																				"subject": "player"
																			}
																		],
																		"is_minified": true,
																		"children": {
																			"test": "is_family",
																			"subject": "player"
																		}
																	}
																]
															}
														]
													}
												]
											}
										]
									}
								]
							},
							{
								"key": "minecraft:behavior.hurt_by_target",
								"is_minified": true,
								"children": {
									"priority": 0
								}
							}
						]
					},
					{
						"open": {
							"description": {
								"identifier": "ark:root",
								"is_summonable": true,
								"is_spawnable": false,
								"is_experimental": false
							},
							"component_groups": {},
							"components": {
								"minecraft:movement": {
									"value": 0
								},
								"minecraft:movement.basic": {
									"max_turn": 30
								},
								"minecraft:attack": {
									"damage": 3
								},
								"minecraft:area_attack": {
									"damage_range": 0.2,
									"damage_per_tick": 1,
									"cause": "contact"
								},
								"minecraft:type_family": {
									"family": [
										"mob",
										"plant"
									]
								},
								"minecraft:collision_box": {
									"width": 1,
									"height": 2.5
								},
								"minecraft:health": {
									"max": 40,
									"value": 40
								},
								"minecraft:pushable": {
									"is_pushable": false,
									"is_pushable_by_piston": false
								},
								"minecraft:physics": {},
								"minecraft:behavior.look_at_target": {
									"priority": 0
								},
								"minecraft:behavior.nearest_attackable_target": {
									"priority": 1,
									"must_see": true,
									"within_radius": 10,
									"entity_types": [
										{
											"filters": {
												"any_of": [
													{
														"test": "is_family",
														"subject": "player"
													}
												]
											}
										}
									]
								},
								"minecraft:behavior.hurt_by_target": {
									"priority": 0
								}
							},
							"events": {}
						},
						"key": "events",
						"is_minified": true,
						"children": {}
					}
				]
			}
		]
	}
}